[
    {
        "id": 1,
        "title": "CMS Integration",
        "image": "https://miro.medium.com/max/1400/1*-dbPsi8Mdqj5Y0454eGvPQ.png",
        "text": "Crate API service E-Commerce Development. This Application can provode a product and category the need ecoomerce",
        "langs" : ["JS", "ExpressJS", "API", "MYSQL", "NodeJS"],
        "url" : "https://github.com/Aldyy123/backend-ecoomerce"
    },
    {
        "id": 2,
        "title": "API SD Alkhairiyah",
        "image": "/projects/api-consultant.png",
        "langs" : ["PHP", "Laravel"],
        "url" : "https://sdalkhairiyyahtegal.sch.id/",
        "text": "Create API for elementary school, and need API can provide more information about the school and then the system can create tracking "
    },
    {
        "id": 4,
        "title": "Restaurant",
        "image": "/projects/resto.png",
        "url" : "https://github.com/Aldyy123/Restaurants-apps",
        "langs" : ["JS", "CSS", "Webpack", "API"],
        "text": "Application list a place restaurant using API from Dicoding"
    },
    {
        "id": 5,
        "title": "Book Journal Excel",
        "image": "https://raw.githubusercontent.com/Aldyy123/pebukuan-excel/master/doc/system.png",
        "url" : "https://github.com/Aldyy123/pebukuan-excel",
        "langs" : ["Python"],
        "text": "Application for recording the finance using the python that can record with automatically in excel"
    },
    {
        "id": 6,
        "title": "CRUD Tours and Visitors",
        "url" : "https://github.com/Aldyy123/bnsp",
        "image": "/projects/wisata.png",
        "langs" : ["PHP", "Bootstrap", "MYSQL"],
        "text": "CRUD tour is an application that can the order tickets for tours for visitors"
    },
    {
        "id": 7,
        "title" : "TeknisiKuAja",
        "url" : "https://github.com/Aldyy123/teknisikuaja",
        "image" : "https://raw.githubusercontent.com/Aldyy123/teknisikuaja/master/doc/preview.png",
        "langs" : ["Laravel", "JavaScript", "CSS", "PHP", "Bootstrap", "MYSQL", "HTML", "Tailwind"],
        "text" : "Application Teknisiku is an innovation developed by my team to users needs which experience the mistake with devices electronic"
    },
    {
        "id": 8,
        "title" : "Post Article",
        "url" : "https://github.com/Aldyy123/rakamin-vi",
        "image" : "https://miro.medium.com/max/1400/1*-dbPsi8Mdqj5Y0454eGvPQ.png",
        "langs" : ["Laravel", "JavaScript", "CSS", "PHP", "MYSQL", "HTML", "Tailwind", "Unit Testing"],
        "text" : "Rest API using laravel, MySQL and Unit Testing. Challenges from rakamin x Investree Virtual Internship"
    },
    {
        "id": 9,
        "title" : "BookShelf API",
        "url" : "https://github.com/Aldyy123/bookshelf-api",
        "image" : "https://miro.medium.com/max/1400/1*-dbPsi8Mdqj5Y0454eGvPQ.png",
        "langs" : ["Hapi JS", "JavaScript", "NodeJS"],
        "text" : "Bookshelf API Challenges from Dicoding"
    },
    {
        "id": 10,
        "title" : "Arsy Digicom",
        "url" : "https://taupe-puffpuff-a9d761.netlify.app/",
        "image" : "/projects/landing-arsy.png",
        "langs" : ["React Js", "JavaScript"],
        "text" : "Project website in services"
    },
    {
        "id": 11,
        "title" : "Backend API Product and Blog",
        "url" : "https://github.com/Aldyy123/new-backend",
        "image" : "https://miro.medium.com/max/1400/1*-dbPsi8Mdqj5Y0454eGvPQ.png",
        "langs" : ["ExpressJS", "NodeJS",  "JavaScript"],
        "text" : "API Product and Blog"
    },
    {
        "id": 12,
        "title" : "Create Dashboard for Employes Management and Product from client",
        "url" : "https://experience.myskill.id/",
        "image" : "/projects/myskill-project.png",
        "langs" : ["Next JS", "React Js",  "JavaScript", "Tailwind", "Rest API", "Redux Toolkit", "Redux"],
        "text" : "Create applications that function to manage employees for companies in need"
    },
    {
        "id": 13,
        "title" : "Calender Event for Halal Kemanag RI",
        "url" : "https://kalender.halal.go.id",
        "image" : "/projects/calender.png",
        "langs" : ["Next JS", "React Js",  "JavaScript", "Tailwind", "Rest API"],
        "text" : "Apps for create event and can show in the calender, then reading the article can be found"
    },
    {
        "id": 14,
        "title" : "App Android for People Disability (Tuna Netra)",
        "url" : "https://github.com/Aldyy123/tracking-disabilitas",
        "image" : "/projects/track-disability.jpg",
        "langs" : ["React Js", "React Native",  "Typescript", "Rest API", "Redux Toolkit", "Redux", "MapBox"],
        "text" : "App Android for tracking People Disability (Tuna Netra) with android then integration with maps, and this app must be additional devices like the stick for person disability"
    },
    {
        "id": 15,
        "title" : "REST APIs AUTOMATE Campus",
        "url" : "https://github.com/Aldyy123/campus-backend",
        "image" : "https://miro.medium.com/max/1400/1*-dbPsi8Mdqj5Y0454eGvPQ.png",
        "langs" : ["Node JS", "ExpressJS",  "JavaScript", "Postgree", "Rest API", "SQL", "Cloud Computing", "GCP"],
        "text" : "Create APIs with system automate schedules and review lessons from students and lecturers in campus. This project is for my final project in Bangkit 2023"
    }
]